fish/__init__.py
fish/main.py
fishfish-0.0.2.dist-info/METADATA
fishfish-0.0.2.dist-info/WHEEL
fishfish-0.0.2.dist-info/top_level.txt
fishfish-0.0.2.dist-info/RECORD
