Metadata-Version: 2.1
Name: fishfish
Version: 0.0.2
Summary: just test
Author: fmc123653
Author-email: fmc0315@126.com
License: apache 3.0
Platform: UNKNOWN
